{
  "content": [
    {
      "path": "de-DE.locPak",
      "size": 2203,
      "date": 132408494923420641
    },
    {
      "path": "en-US.locPak",
      "size": 1806,
      "date": 132408494923400647
    },
    {
      "path": "es-ES.locPak",
      "size": 2000,
      "date": 132408494923391080
    },
    {
      "path": "fr-FR.locPak",
      "size": 2050,
      "date": 132408494923420641
    },
    {
      "path": "it-IT.locPak",
      "size": 2014,
      "date": 132408494923430644
    },
    {
      "path": "pl-PL.locPak",
      "size": 2151,
      "date": 132408494923391080
    },
    {
      "path": "pt-BR.locPak",
      "size": 1952,
      "date": 132408494923380630
    },
    {
      "path": "ru-RU.locPak",
      "size": 2967,
      "date": 132408494923410865
    },
    {
      "path": "SimObjects/Airplanes/Asobo_TBM930/engines.cfg",
      "size": 15587,
      "date": 132387737630000000
    },
    {
      "path": "SimObjects/Airplanes/Asobo_TBM930/systems.cfg",
      "size": 7916,
      "date": 132387737630000000
    },
    {
      "path": "ModelBehaviorDefs/Asobo/Common/Deice.xml",
      "size": 9954,
      "date": 132395409590000000
    }
  ]
}